streamlit_theme/__init__.py
streamlit_theme/__main__.py
streamlit_theme/example.py
streamlit_theme/frontend/dist/index.html
streamlit_theme/frontend/dist/assets/index--ZWO88yE.js
streamlit_theme/frontend/dist/assets/index-3Jrapfwd.css
st_theme-1.2.3.dist-info/LICENSE
st_theme-1.2.3.dist-info/METADATA
st_theme-1.2.3.dist-info/WHEEL
st_theme-1.2.3.dist-info/entry_points.txt
st_theme-1.2.3.dist-info/top_level.txt
st_theme-1.2.3.dist-info/RECORD
