Metadata-Version: 2.1
Name: st-theme
Version: 1.2.3
Summary: A component that returns the active theme of the Streamlit app.
Home-page: https://github.com/gabrieltempass/streamlit-theme
Author: Gabriel Tem Pass
Author-email: redo_hint_0x@icloud.com
License: MIT License
Project-URL: Source Code, https://github.com/gabrieltempass/streamlit-theme
Project-URL: Bug Tracker, https://github.com/gabrieltempass/streamlit-theme/issues
Project-URL: Release notes, https://github.com/gabrieltempass/streamlit-theme/releases
Project-URL: Documentation, https://github.com/gabrieltempass/streamlit-theme
Project-URL: Community, https://discuss.streamlit.io/t/new-component-st-theme-it-returns-the-active-theme-of-the-streamlit-app/64424
Platform: UNKNOWN
Classifier: Development Status :: 5 - Production/Stable
Classifier: Environment :: Console
Classifier: Environment :: Web Environment
Classifier: Intended Audience :: Developers
Classifier: Intended Audience :: Science/Research
Classifier: License :: OSI Approved :: MIT License
Classifier: Programming Language :: Python :: 3.8
Classifier: Programming Language :: Python :: 3.9
Classifier: Programming Language :: Python :: 3.10
Classifier: Programming Language :: Python :: 3.11
Classifier: Programming Language :: Python :: 3.12
Classifier: Topic :: Database :: Front-Ends
Classifier: Topic :: Office/Business :: Financial :: Spreadsheet
Classifier: Topic :: Scientific/Engineering :: Information Analysis
Classifier: Topic :: Scientific/Engineering :: Visualization
Classifier: Topic :: Software Development :: Libraries :: Application Frameworks
Classifier: Topic :: Software Development :: Widget Sets
Requires-Python: >=3.8
License-File: LICENSE
